csw/__init__.py
csw/csw.py
csw/d2n.py
csw/kk.py
csw/n2d.py
csw/n2o.py
csw/n2q.py
csw/o2n.py
csw/q2n.py
csw/spj.py
csw-0.3.4.dist-info/METADATA
csw-0.3.4.dist-info/WHEEL
csw-0.3.4.dist-info/entry_points.txt
csw-0.3.4.dist-info/top_level.txt
csw-0.3.4.dist-info/RECORD
