Metadata-Version: 2.1
Name: csw
Version: 0.3.4
Summary: 文自在変換ツール
Home-page: https://github.com/Sone-i/csw
Author: Sone-i
Author-email: i18308@kagawa.kosen-ac.jp
License: UNKNOWN
Download-URL: https://github.com/Sone-i/csw
Platform: UNKNOWN
Classifier: Programming Language :: Python :: 3
Classifier: License :: OSI Approved :: MIT License
Requires-Python: >=3.7
Requires-Dist: MeCab (>=0.996)
